authed/__init__.py
authed/cli/auth.py
authed/cli/main.py
authed/cli/utils.py
authed/cli/commands/agents.py
authed/cli/commands/init.py
authed/cli/commands/keys.py
authed/cli/commands/logs.py
authed/cli/commands/permissions.py
authed/sdk/__init__.py
authed/sdk/config.py
authed/sdk/exceptions.py
authed/sdk/manager.py
authed/sdk/models.py
authed/sdk/auth/__init__.py
authed/sdk/auth/agent_auth.py
authed/sdk/auth/dpop.py
authed/sdk/auth/tokens.py
authed/sdk/channel/__init__.py
authed/sdk/channel/channel.py
authed/sdk/channel/manager.py
authed/sdk/channel/protocol.py
authed/sdk/channel/utils.py
authed/sdk/channel/websocket.py
authed/sdk/decorators/__init__.py
authed/sdk/decorators/incoming/fastapi.py
authed/sdk/decorators/outgoing/httpx.py
authed/sdk/decorators/outgoing/requests.py
authed/sdk/server/__init__.py
authed/sdk/server/websocket.py
authed/sdk/testing/test_agents/agent_a.py
authed/sdk/testing/test_agents/agent_b.py
authed/sdk/testing/test_agents/message_recorder.py
authed/sdk/testing/test_agents/run_test.py
authed/sdk/utils/url.py
authed-0.2.5.dist-info/METADATA
authed-0.2.5.dist-info/WHEEL
authed-0.2.5.dist-info/entry_points.txt
authed-0.2.5.dist-info/top_level.txt
authed-0.2.5.dist-info/RECORD
