Metadata-Version: 2.4
Name: authed
Version: 0.2.5
Summary: Agent authentication SDK for secure service-to-service communication
Author-email: Antoni Gmitruk <antoni@getauthed.dev>
Project-URL: Documentation, https://docs.getauthed.dev
Project-URL: Source code, https://github.com/authed-dev/authed
Classifier: Development Status :: 3 - Alpha
Classifier: Intended Audience :: Developers
Classifier: License :: OSI Approved :: MIT License
Classifier: Programming Language :: Python :: 3
Classifier: Programming Language :: Python :: 3.8
Classifier: Programming Language :: Python :: 3.9
Classifier: Programming Language :: Python :: 3.10
Classifier: Programming Language :: Python :: 3.11
Classifier: Topic :: Security
Classifier: Topic :: Software Development :: Libraries :: Python Modules
Classifier: Topic :: System :: Systems Administration :: Authentication/Directory
Requires-Python: >=3.8
Requires-Dist: click>=8.1.8
Requires-Dist: httpx>=0.28.1
Requires-Dist: pydantic>=2.10.6
Requires-Dist: cryptography>=44.0.0
Requires-Dist: pyjwt>=2.10.1
Requires-Dist: websockets>=15.0.1
Requires-Dist: uvicorn[standard]>=0.34.0
Requires-Dist: authed-mcp>=0.2.0
